MANIFEST.in
README.md
pyproject.toml
setup.py
amuse_aarsethzare.egg-info/PKG-INFO
amuse_aarsethzare.egg-info/SOURCES.txt
amuse_aarsethzare.egg-info/dependency_links.txt
amuse_aarsethzare.egg-info/requires.txt
amuse_aarsethzare.egg-info/top_level.txt
src/amuse/community/aarsethzare/Makefile
src/amuse/community/aarsethzare/__init__.py
src/amuse/community/aarsethzare/_version.py
src/amuse/community/aarsethzare/interface.f90
src/amuse/community/aarsethzare/interface.py
src/amuse/community/aarsethzare/src/AarsethZare.f
src/amuse/community/aarsethzare/src/Makefile
src/amuse/community/aarsethzare/src/block.f
src/amuse/community/aarsethzare/src/data.f
src/amuse/community/aarsethzare/src/derqp.f
src/amuse/community/aarsethzare/src/difsy1.f
src/amuse/community/aarsethzare/src/euler.f
src/amuse/community/aarsethzare/src/peri.f
src/amuse/community/aarsethzare/src/test.f90
src/amuse/community/aarsethzare/src/transf.f
src/amuse/community/aarsethzare/src/transform.f
src/amuse/community/aarsethzare/src/triple.f
support/__init__.py
support/classifiers.py
support/config.py
support/generate_main.py
support/getsp.class
support/getsp.java
support/misc.py
support/setup_codes.py
support/version.py